ci_cd_apier/__init__.py
ci_cd_apier/apier.py
ci_cd_apier/client.py
ci_cd_apier/constants.py
ci_cd_apier/exceptions.py
ci_cd_apier/patcher.py
ci_cd_apier/postprocessor.py
ci_cd_apier/preprocessor.py
ci_cd_apier/js/apier.js
ci_cd_apier/js/agewasm/LICENSE
ci_cd_apier/js/agewasm/age.wasm
ci_cd_apier/js/agewasm/wasm_exec.js
ci_cd_apier-2.0.0.dist-info/LICENSE.txt
ci_cd_apier-2.0.0.dist-info/METADATA
ci_cd_apier-2.0.0.dist-info/WHEEL
ci_cd_apier-2.0.0.dist-info/top_level.txt
ci_cd_apier-2.0.0.dist-info/RECORD
