Metadata-Version: 2.1
Name: ci-cd-apier
Version: 2.0.0
Summary: ci-cd-APIer -- Flask-like API framework for GitLab CI/CD pipelines
Author-email: Adam Hlavacek <git@adamhlavacek.com>
Project-URL: Homepage, https://github.com/esoadamo/ci-cd-apier
Project-URL: Issues, https://github.com/esoadamo/ci-cd-apier/issues
Classifier: Programming Language :: Python :: 3
Classifier: License :: OSI Approved :: GNU General Public License v3 (GPLv3)
Classifier: Operating System :: OS Independent
License-File: LICENSE.txt
Requires-Dist: ssage ==1.5.1
Requires-Dist: Jinja2 ==3.1.6
